nvremap.cpython-38-x86_64-linux-gnu.so
nvremap-0.1.4.dist-info/LICENSE
nvremap-0.1.4.dist-info/METADATA
nvremap-0.1.4.dist-info/WHEEL
nvremap-0.1.4.dist-info/top_level.txt
nvremap-0.1.4.dist-info/RECORD
