Metadata-Version: 2.1
Name: nvremap
Version: 0.1.4
Summary: Image remapping using NVIDIA GPU
Home-page: https://github.com/ArtificialNotImbecile/nvRemap
Author: Yongxiang Luo
License: MIT
Project-URL: Source, https://github.com/ArtificialNotImbecile/nvRemap
Project-URL: Tracker, https://github.com/ArtificialNotImbecile/nvRemap/issues
Keywords: pynvremap,nvremap,image remap,gpu,nvidia
Platform: UNKNOWN
Classifier: Development Status :: 3 - Alpha
Classifier: Programming Language :: Python :: 3 :: Only
Classifier: License :: OSI Approved :: MIT License
Classifier: Operating System :: POSIX :: Linux
Classifier: Environment :: GPU :: NVIDIA CUDA :: 11.0
Requires-Python: >=3.6
License-File: LICENSE
Requires-Dist: numpy
